setup.cfg
setup.py
connectiontests/__init__.py
connectiontests/conn_test1.py
connectiontests/test1.py
taobao_tmc_py.egg-info/PKG-INFO
taobao_tmc_py.egg-info/SOURCES.txt
taobao_tmc_py.egg-info/dependency_links.txt
taobao_tmc_py.egg-info/entry_points.txt
taobao_tmc_py.egg-info/not-zip-safe
taobao_tmc_py.egg-info/requires.txt
taobao_tmc_py.egg-info/top_level.txt
taobaotmcpy/__init__.py
taobaotmcpy/event.py
taobaotmcpy/message.py
taobaotmcpy/messageio.py
taobaotmcpy/messagetype.py
taobaotmcpy/tmcclient.py
taobaotmcpy/tornadowebsocket.py
taobaotmcpy/utils.py
unpacktests/__init__.py
unpacktests/test.py
unpacktests/unpack_test1.py
unpacktests/unpack_test2.py