Metadata-Version: 1.0
Name: taobao-tmc-py
Version: 0.1dev-r0
Summary: 淘宝平台消息服务python版本
Home-page: https://github.com/baocaixiong/taobao-tmc-python
Author: baocaixiong
Author-email: baocaixiong@gmail.com
License: MIT
Keywords: taobao tmc python
Platform: UNKNOWN
